{
  "female_n": { "value": 46675, "citation": "46,675 (27%) of 174,149 participants were women", "confidence": 0.96 },
  "female_pct": { "value": 27.0, "citation": "46,675 (27%) of 174,149 participants were women", "confidence": 0.96 },
  "total_n": { "value": 174149, "citation": "174,149 participants", "confidence": 0.96 },
  "sex_stratified_efficacy_reported": { "value": "yes", "citation": "Proportional reductions per 1.0 mmol/L LDL reduction in major vascular events were similar in women (RR 0.84) and men (RR 0.78)", "confidence": 0.95 },
  "sex_stratified_safety_reported": { "value": "uncertain", "citation": "with no significant heterogeneity by sex", "confidence": 0.6 },
  "sex_by_treatment_interaction_tested": { "value": "yes", "citation": "with no significant heterogeneity by sex", "confidence": 0.9 },
  "menopausal_status_reported": { "value": "not_reported", "citation": null, "confidence": 0.0 },
  "hormonal_factors_reported": { "value": "not_reported", "citation": null, "confidence": 0.0 },
  "hormone_therapy_reported": { "value": "not_reported", "citation": null, "confidence": 0.0 },
  "pregnancy_excluded": { "value": "not_reported", "citation": null, "confidence": 0.0 }
}
